Workbook

Sheet Leia-me
A1: A Firma: planilha de balanceamento v1
A3: Fonte dos números do jogo (issue #33). Dono: Nicolas.
A5: Como usar
A6: 1. Azul = número copiado do asset. Mude aqui pra testar e veja as abas recalcularem.
A7: 2. Amarelo (aba Config) = cenário: nível da crew e dos upgrades que você quer olhar.
A8: 3. Gostou? Leve o número pro asset no Unity (GameConfig, HeistDef, UpgradeDef) e rode o simulador:
A9: python docs/balanceamento/simulador.py
A10: 4. Registre a mudança no docs/BALANCEAMENTO.md (Registro de ajustes).
A12: Abas
A13: Config: números globais e o cenário · Ladrões: atributos e XP por nível · Upgrades: custo por nível
A14: Golpes: tempo e alerta sala a sala, resumo e tabela por nível da crew · Bicos: renda e offline
A15: Recrutas: preço por nível · Curva: metas de tempo × simulação, e o que mudou na v1
A17: Cores: azul = entrada · preto = fórmula · verde = valor puxado de outra aba · vermelho/verde nas tabelas = toca/não toca sirene

Sheet Config
A1: Config global e cenário
A2: Azul = número copiado do GameConfig.asset (mude aqui pra testar, depois leve pro asset). Amarelo = cenário que você escolhe.
A4: Campo | B4: Valor | C4: Onde fica / o que é
A5: noSpecialistPowerFactor | B5: 0.35 | C5: Poder sem especialista = fator × maior Perícia
A6: noSpecialistAlertMult | B6: 2 | C6: Alerta sem especialista é multiplicado por isso
A7: stealthAlertFactor | B7: 0.5 | C7: Quanto a Discrição média corta do alerta (0,5 = até −50%)
A8: policeCountdownSeconds | B8: 10 | C8: Segundos da sirene até a polícia chegar
A9: hastyEscapeLootKeep | B9: 0.8 | C9: Sacola na fuga apressada (com sirene)
A10: forcedEscapeLootKeep | B10: 0.5 | C10: Sacola na fuga forçada (polícia chegou)
A11: baseArrestChance | B11: 0.4 | C11: Chance base de prisão na fuga forçada
A12: xpPerRoom | B12: 1 | C12: XP por sala limpa
A13: xpPerLevelFactor | B13: 5 | C13: XP pro próximo nível = fator × nível
A14: maxLevel | B14: 10 | C14: Nível máximo do ladrão
A15: recruitBaseCost | B15: 50 | C15: Recruta nível 1
A16: recruitCostGrowthPerLevel | B16: 1.8 | C16: Crescimento do preço do recruta por nível
... A23: wantedAlertMult | B23: 1.1 | C23: Procurado: alerta × isso por nível
A25: Cenário (usado nas abas Golpes e Bicos)
A26: Nível da crew | B26: 3 | C26: Nível dos especialistas no golpe (1 a 10)
A27: Nível de Ferramentas | B27: 2 | C27: Upgrade: +Perícia de todos
A28: Nível de Tênis de molinha | B28: 2 | C28: Upgrade: +Discrição de todos
A29: Nível de Lavanderia | B29: 0 | C29: Upgrade: +% de todo loot
A30: Nível de Ponto de bico | B30: 0 | C30: Upgrade: +% de renda dos bicos

Sheet Ladrões
A1: Atributos por nível (sem a variação de ±15% do sorteio)
A3: Tipo | B3: Perícia base | C3: Discrição base | D3: Perícia/nível | E3: Discrição/nível | F3: +s na polícia | G3: +sacola na fuga
A4: Gazua | B4: 35 | C4: 30 | D4: 7 | E4: 4 | F4: 0 | G4: 0
A5: Disquete | B5: 35 | C5: 35 | D5: 7 | E5: 4 | F5: 0 | G5: 0
A6: 171 | B6: 35 | C6: 30 | D6: 7 | E6: 4 | F6: 0 | G6: 0
A7: Pé-na-Tábua | B7: 25 | C7: 30 | D7: 7 | E7: 4 | F7: 4 | G7: 0.1
A10: Perícia por nível
A11: Tipo | B11: Nv 1 | C11: Nv 2 | D11: Nv 3 | E11: Nv 4 | F11: Nv 5 | G11: Nv 6 | H11: Nv 7 | I11: Nv 8 | J11: Nv 9 | K11: Nv 10
A12: Gazua | B12: =$B$4+$D$4*(1-1) | C12: =$B$4+$D$4*(2-1) | D12: =$B$4+$D$4*(3-1) | E12: =$B$4+$D$4*(4-1) | F12: =$B$4+$D$4*(5-1) | G12: =$B$4+$D$4*(6-1) | H12: =$B$4+$D$4*(7-1) | I12: =$B$4+$D$4*(8-1) | J12: =$B$4+$D$4*(9-1) | K12: =$B$4+$D$4*(10-1)
A13: Disquete | B13: =$B$5+$D$5*(1-1) | C13: =$B$5+$D$5*(2-1) | D13: =$B$5+$D$5*(3-1) | E13: =$B$5+$D$5*(4-1) | F13: =$B$5+$D$5*(5-1) | G13: =$B$5+$D$5*(6-1) | H13: =$B$5+$D$5*(7-1) | I13: =$B$5+$D$5*(8-1) | J13: =$B$5+$D$5*(9-1) | K13: =$B$5+$D$5*(10-1)
A14: 171 | B14: =$B$6+$D$6*(1-1) | C14: =$B$6+$D$6*(2-1) | D14: =$B$6+$D$6*(3-1) | E14: =$B$6+$D$6*(4-1) | F14: =$B$6+$D$6*(5-1) | G14: =$B$6+$D$6*(6-1) | H14: =$B$6+$D$6*(7-1) | I14: =$B$6+$D$6*(8-1) | J14: =$B$6+$D$6*(9-1) | K14: =$B$6+$D$6*(10-1)
A15: Pé-na-Tábua | B15: =$B$7+$D$7*(1-1) | C15: =$B$7+$D$7*(2-1) | D15: =$B$7+$D$7*(3-1) | E15: =$B$7+$D$7*(4-1) | F15: =$B$7+$D$7*(5-1) | G15: =$B$7+$D$7*(6-1) | H15: =$B$7+$D$7*(7-1) | I15: =$B$7+$D$7*(8-1) | J15: =$B$7+$D$7*(9-1) | K15: =$B$7+$D$7*(10-1)
A17: Discrição por nível
A18: Tipo | B18: Nv 1 | C18: Nv 2 | D18: Nv 3 | E18: Nv 4 | F18: Nv 5 | G18: Nv 6 | H18: Nv 7 | I18: Nv 8 | J18: Nv 9 | K18: Nv 10
A19: Gazua | B19: =$C$4+$E$4*(1-1) | C19: =$C$4+$E$4*(2-1) | D19: =$C$4+$E$4*(3-1) | E19: =$C$4+$E$4*(4-1) | F19: =$C$4+$E$4*(5-1) | G19: =$C$4+$E$4*(6-1) | H19: =$C$4+$E$4*(7-1) | I19: =$C$4+$E$4*(8-1) | J19: =$C$4+$E$4*(9-1) | K19: =$C$4+$E$4*(10-1)
A20: Disquete | B20: =$C$5+$E$5*(1-1) | C20: =$C$5+$E$5*(2-1) | D20: =$C$5+$E$5*(3-1) | E20: =$C$5+$E$5*(4-1) | F20: =$C$5+$E$5*(5-1) | G20: =$C$5+$E$5*(6-1) | H20: =$C$5+$E$5*(7-1) | I20: =$C$5+$E$5*(8-1) | J20: =$C$5+$E$5*(9-1) | K20: =$C$5+$E$5*(10-1)
A21: 171 | B21: =$C$6+$E$6*(1-1) | C21: =$C$6+$E$6*(2-1) | D21: =$C$6+$E$6*(3-1) | E21: =$C$6+$E$6*(4-1) | F21: =$C$6+$E$6*(5-1) | G21: =$C$6+$E$6*(6-1) | H21: =$C$6+$E$6*(7-1) | I21: =$C$6+$E$6*(8-1) | J21: =$C$6+$E$6*(9-1) | K21: =$C$6+$E$6*(10-1)
A22: Pé-na-Tábua | B22: =$C$7+$E$7*(1-1) | C22: =$C$7+$E$7*(2-1) | D22: =$C$7+$E$7*(3-1) | E22: =$C$7+$E$7*(4-1) | F22: =$C$7+$E$7*(5-1) | G22: =$C$7+$E$7*(6-1) | H22: =$C$7+$E$7*(7-1) | I22: =$C$7+$E$7*(8-1) | J22: =$C$7+$E$7*(9-1) | K22: =$C$7+$E$7*(10-1)
A24: XP
A25: Conta | B25: Nv 1 | C25: Nv 2 | D25: Nv 3 | E25: Nv 4 | F25: Nv 5 | G25: Nv 6 | H25: Nv 7 | I25: Nv 8 | J25: Nv 9 | K25: Nv 10
A26: XP pro próximo nível | B26: =IF(1>=Config!$B$14,0,Config!$B$13*1) | C26: =IF(2>=Config!$B$14,0,Config!$B$13*2) | D26: =IF(3>=Config!$B$14,0,Config!$B$13*3) | E26: =IF(4>=Config!$B$14,0,Config!$B$13*4) | F26: =IF(5>=Config!$B$14,0,Config!$B$13*5) | G26: =IF(6>=Config!$B$14,0,Config!$B$13*6) | H26: =IF(7>=Config!$B$14,0,Config!$B$13*7) | I26: =IF(8>=Config!$B$14,0,Config!$B$13*8) | J26: =IF(9>=Config!$B$14,0,Config!$B$13*9) | K26: =IF(10>=Config!$B$14,0,Config!$B$13*10)
A27: Salas limpas até chegar no nível | B27: =0 | C27: =B27+B26/Config!$B$12 | D27: =C27+C26/Config!$B$12 | E27: =D27+D26/Config!$B$12 | F27: =E27+E26/Config!$B$12 | G27: =F27+F26/Config!$B$12 | H27: =G27+G26/Config!$B$12 | I27: =H27+H26/Config!$B$12 | J27: =I27+I26/Config!$B$12 | K27: =J27+J26/Config!$B$12

Sheet Upgrades
A1: Upgrades do esconderijo: custo = custo base × crescimento^nível
A3: id | B3: Nome | C3: Efeito | D3: Custo base | E3: Crescimento | F3: Nível máx | G3: Valor/nível | H3: Efeito no máx | I3: Custo total | J3: Nv 1 | K3: Nv 2 | L3: Nv 3 | M3: Nv 4 | N3: Nv 5 | O3: Nv 6 | P3: Nv 7 | Q3: Nv 8 | R3: Nv 9 | S3: Nv 10
A4: van | B4: Van | C4: +vaga no golpe | D4: 300 | E4: 4 | F4: 2 | G4: 1 | H4: =F4*G4 | I4: =SUM(J4:S4) | J4: =IF(1<=$F4,ROUND($D4*$E4^(1-1),0),"") | K4: =IF(2<=$F4,ROUND($D4*$E4^(2-1),0),"") | L4: =IF(3<=$F4,ROUND($D4*$E4^(3-1),0),"") | M4: =IF(4<=$F4,ROUND($D4*$E4^(4-1),0),"") | N4: =IF(5<=$F4,ROUND($D4*$E4^(5-1),0),"") | O4: =IF(6<=$F4,ROUND($D4*$E4^(6-1),0),"") | P4: =IF(7<=$F4,ROUND($D4*$E4^(7-1),0),"") | Q4: =IF(8<=$F4,ROUND($D4*$E4^(8-1),0),"") | R4: =IF(9<=$F4,ROUND($D4*$E4^(9-1),0),"") | S4: =IF(10<=$F4,ROUND($D4*$E4^(10-1),0),"")
A5: quartos | B5: Quartos | C5: +vaga na crew | D5: 200 | E5: 2.2 | F5: 5 | G5: 1 | H5: =F5*G5 | I5: =SUM(J5:S5) | J5: =IF(1<=$F5,ROUND($D5*$E5^(1-1),0),"") | K5: =IF(2<=$F5,ROUND($D5*$E5^(2-1),0),"") | L5: =IF(3<=$F5,ROUND($D5*$E5^(3-1),0),"") | M5: =IF(4<=$F5,ROUND($D5*$E5^(4-1),0),"") | N5: =IF(5<=$F5,ROUND($D5*$E5^(5-1),0),"") | O5: =IF(6<=$F5,ROUND($D5*$E5^(6-1),0),"") | P5: =IF(7<=$F5,ROUND($D5*$E5^(7-1),0),"") | Q5: =IF(8<=$F5,ROUND($D5*$E5^(8-1),0),"") | R5: =IF(9<=$F5,ROUND($D5*$E5^(9-1),0),"") | S5: =IF(10<=$F5,ROUND($D5*$E5^(10-1),0),"")
A6: ferramentas | B6: Ferramentas | C6: +% Perícia | D6: 150 | E6: 1.6 | F6: 10 | G6: 5 | H6: =F6*G6 | I6: =SUM(J6:S6) | J6: =IF(1<=$F6,ROUND($D6*$E6^(1-1),0),"") | K6: =IF(2<=$F6,ROUND($D6*$E6^(2-1),0),"") | L6: =IF(3<=$F6,ROUND($D6*$E6^(3-1),0),"") | M6: =IF(4<=$F6,ROUND($D6*$E6^(4-1),0),"") | N6: =IF(5<=$F6,ROUND($D6*$E6^(5-1),0),"") | O6: =IF(6<=$F6,ROUND($D6*$E6^(6-1),0),"") | P6: =IF(7<=$F6,ROUND($D6*$E6^(7-1),0),"") | Q6: =IF(8<=$F6,ROUND($D6*$E6^(8-1),0),"") | R6: =IF(9<=$F6,ROUND($D6*$E6^(9-1),0),"") | S6: =IF(10<=$F6,ROUND($D6*$E6^(10-1),0),"")
A7: tenis-de-molinha | B7: Tênis de molinha | C7: +% Discrição | D7: 150 | E7: 1.6 | F7: 10 | G7: 5 | H7: =F7*G7 | I7: =SUM(J7:S7) | J7: =IF(1<=$F7,ROUND($D7*$E7^(1-1),0),"") | K7: =IF(2<=$F7,ROUND($D7*$E7^(2-1),0),"") | L7: =IF(3<=$F7,ROUND($D7*$E7^(3-1),0),"") | M7: =IF(4<=$F7,ROUND($D7*$E7^(4-1),0),"") | N7: =IF(5<=$F7,ROUND($D7*$E7^(5-1),0),"") | O7: =IF(6<=$F7,ROUND($D7*$E7^(6-1),0),"") | P7: =IF(7<=$F7,ROUND($D7*$E7^(7-1),0),"") | Q7: =IF(8<=$F7,ROUND($D7*$E7^(8-1),0),"") | R7: =IF(9<=$F7,ROUND($D7*$E7^(9-1),0),"") | S7: =IF(10<=$F7,ROUND($D7*$E7^(10-1),0),"")
A8: advogado | B8: Advogado de porta de cadeia | C8: −% prisão e fiança | D8: 250 | E8: 1.8 | F8: 5 | G8: 10 | H8: =F8*G8 | I8: =SUM(J8:S8) | J8: =IF(1<=$F8,ROUND($D8*$E8^(1-1),0),"") | K8: =IF(2<=$F8,ROUND($D8*$E8^(2-1),0),"") | L8: =IF(3<=$F8,ROUND($D8*$E8^(3-1),0),"") | M8: =IF(4<=$F8,ROUND($D8*$E8^(4-1),0),"") | N8: =IF(5<=$F8,ROUND($D8*$E8^(5-1),0),"") | O8: =IF(6<=$F8,ROUND($D8*$E8^(6-1),0),"") | P8: =IF(7<=$F8,ROUND($D8*$E8^(7-1),0),"") | Q8: =IF(8<=$F8,ROUND($D8*$E8^(8-1),0),"") | R8: =IF(9<=$F8,ROUND($D8*$E8^(9-1),0),"") | S8: =IF(10<=$F8,ROUND($D8*$E8^(10-1),0),"")
A9: contatos | B9: Contatos | C9: +nível dos recrutas | D9: 400 | E9: 2 | F9: 5 | G9: 1 | H9: =F9*G9 | I9: =SUM(J9:S9) | J9: =IF(1<=$F9,ROUND($D9*$E9^(1-1),0),"") | K9: =IF(2<=$F9,ROUND($D9*$E9^(2-1),0),"") | L9: =IF(3<=$F9,ROUND($D9*$E9^(3-1),0),"") | M9: =IF(4<=$F9,ROUND($D9*$E9^(4-1),0),"") | N9: =IF(5<=$F9,ROUND($D9*$E9^(5-1),0),"") | O9: =IF(6<=$F9,ROUND($D9*$E9^(6-1),0),"") | P9: =IF(7<=$F9,ROUND($D9*$E9^(7-1),0),"") | Q9: =IF(8<=$F9,ROUND($D9*$E9^(8-1),0),"") | R9: =IF(9<=$F9,ROUND($D9*$E9^(9-1),0),"") | S9: =IF(10<=$F9,ROUND($D9*$E9^(10-1),0),"")
A10: lavanderia | B10: Lavanderia | C10: +% loot | D10: 500 | E10: 1.7 | F10: 10 | G10: 5 | H10: =F10*G10 | I10: =SUM(J10:S10) | J10: =IF(1<=$F10,ROUND($D10*$E10^(1-1),0),"") | K10: =IF(2<=$F10,ROUND($D10*$E10^(2-1),0),"") | L10: =IF(3<=$F10,ROUND($D10*$E10^(3-1),0),"") | M10: =IF(4<=$F10,ROUND($D10*$E10^(4-1),0),"") | N10: =IF(5<=$F10,ROUND($D10*$E10^(5-1),0),"") | O10: =IF(6<=$F10,ROUND($D10*$E10^(6-1),0),"") | P10: =IF(7<=$F10,ROUND($D10*$E10^(7-1),0),"") | Q10: =IF(8<=$F10,ROUND($D10*$E10^(8-1),0),"") | R10: =IF(9<=$F10,ROUND($D10*$E10^(9-1),0),"") | S10: =IF(10<=$F10,ROUND($D10*$E10^(10-1),0),"")
A11: radio-da-policia | B11: Rádio da polícia | C11: +s na contagem | D11: 350 | E11: 1.8 | F11: 5 | G11: 2 | H11: =F11*G11 | I11: =SUM(J11:S11) | J11: =IF(1<=$F11,ROUND($D11*$E11^(1-1),0),"") | K11: =IF(2<=$F11,ROUND($D11*$E11^(2-1),0),"") | L11: =IF(3<=$F11,ROUND($D11*$E11^(3-1),0),"") | M11: =IF(4<=$F11,ROUND($D11*$E11^(4-1),0),"") | N11: =IF(5<=$F11,ROUND($D11*$E11^(5-1),0),"") | O11: =IF(6<=$F11,ROUND($D11*$E11^(6-1),0),"") | P11: =IF(7<=$F11,ROUND($D11*$E11^(7-1),0),"") | Q11: =IF(8<=$F11,ROUND($D11*$E11^(8-1),0),"") | R11: =IF(9<=$F11,ROUND($D11*$E11^(9-1),0),"") | S11: =IF(10<=$F11,ROUND($D11*$E11^(10-1),0),"")
A12: ponto-de-bico | B12: Ponto de bico | C12: +% renda dos bicos | D12: 100 | E12: 1.6 | F12: 10 | G12: 10 | H12: =F12*G12 | I12: =SUM(J12:S12) | J12: =IF(1<=$F12,ROUND($D12*$E12^(1-1),0),"") | K12: =IF(2<=$F12,ROUND($D12*$E12^(2-1),0),"") | L12: =IF(3<=$F12,ROUND($D12*$E12^(3-1),0),"") | M12: =IF(4<=$F12,ROUND($D12*$E12^(4-1),0),"") | N12: =IF(5<=$F12,ROUND($D12*$E12^(5-1),0),"") | O12: =IF(6<=$F12,ROUND($D12*$E12^(6-1),0),"") | P12: =IF(7<=$F12,ROUND($D12*$E12^(7-1),0),"") | Q12: =IF(8<=$F12,ROUND($D12*$E12^(8-1),0),"") | R12: =IF(9<=$F12,ROUND($D12*$E12^(9-1),0),"") | S12: =IF(10<=$F12,ROUND($D12*$E12^(10-1),0),"")
A14: Custo do nível n = o que se paga pra subir do nível n−1 pro n (Formulas.UpgradeCost).

Sheet Golpes
A1: Golpes sala a sala, no cenário da aba Config (crew com especialista em toda sala)
A2: Poder do especialista: | C2: =(((INDEX(Ladrões!$B$12:$K$12,1,Config!$B$26)+INDEX(Ladrões!$B$13:$K$13,1,Config!$B$26)+INDEX(Ladrões!$B$14:$K$14,1,Config!$B$26))/3)*(1+Config!$B$27*Upgrades!$G$6/100)) | E2: Tempo = dificuldade ÷ poder · Alerta/s real = alerta da sala × (1 − fator × Discrição/100) · sirene em 100.
A3: Discrição média: | C3: =(((INDEX(Ladrões!$B$19:$K$19,1,Config!$B$26)+INDEX(Ladrões!$B$20:$K$20,1,Config!$B$26)+INDEX(Ladrões!$B$21:$K$21,1,Config!$B$26))/3)*(1+Config!$B$28*Upgrades!$G$7/100))
A5: Golpe | B5: # | C5: Sala | D5: Obstáculo | E5: Dificuldade | F5: Loot | G5: Alerta/s | H5: Tempo | I5: Alerta da sala | J5: Alerta acumulado | K5: Loot acumulado
A6: Lotérica do Seu Zé | B6: 1 | C6: Entrada | D6: Pessoa | E6: 250 | F6: 50 | G6: 1.5 | H6: =MAX(0.5,E6/MAX(1,$C$2)) | I6: =G6*(1-Config!$B$7*MIN(1,$C$3/100))*H6 | J6: =SUMIFS($I$6:$I$30,$A$6:$A$30,A6,$B$6:$B$30,"<="&B6) | K6: =SUMIFS($F$6:$F$30,$A$6:$A$30,A6,$B$6:$B$30,"<="&B6)
A7: Lotérica do Seu Zé | B7: 2 | C7: Balcão | D7: Pessoa | E7: 300 | F7: 150 | G7: 2 | H7: =MAX(0.5,E7/MAX(1,$C$2)) | I7: =G7*(1-Config!$B$7*MIN(1,$C$3/100))*H7 | J7: =SUMIFS($I$6:$I$30,$A$6:$A$30,A7,$B$6:$B$30,"<="&B7) | K7: =SUMIFS($F$6:$F$30,$A$6:$A$30,A7,$B$6:$B$30,"<="&B7)
A8: Lotérica do Seu Zé | B8: 3 | C8: Cofrinho | D8: Fechadura | E8: 350 | F8: 300 | G8: 2.5 | H8: =MAX(0.5,E8/MAX(1,$C$2)) | I8: =G8*(1-Config!$B$7*MIN(1,$C$3/100))*H8 | J8: =SUMIFS($I$6:$I$30,$A$6:$A$30,A8,$B$6:$B$30,"<="&B8) | K8: =SUMIFS($F$6:$F$30,$A$6:$A$30,A8,$B$6:$B$30,"<="&B8)
A9: Joalheria Brilho Eterno | B9: 1 | C9: Vitrine | D9: Pessoa | E9: 720 | F9: 300 | G9: 2 | H9: =MAX(0.5,E9/MAX(1,$C$2)) | I9: =G9*(1-Config!$B$7*MIN(1,$C$3/100))*H9 | J9: =SUMIFS($I$6:$I$30,$A$6:$A$30,A9,$B$6:$B$30,"<="&B9) | K9: =SUMIFS($F$6:$F$30,$A$6:$A$30,A9,$B$6:$B$30,"<="&B9)
A10: Joalheria Brilho Eterno | B10: 2 | C10: Sala de Câmeras | D10: Sistema | E10: 880 | F10: 400 | G10: 3 | H10: =MAX(0.5,E10/MAX(1,$C$2)) | I10: =G10*(1-Config!$B$7*MIN(1,$C$3/100))*H10 | J10: =SUMIFS($I$6:$I$30,$A$6:$A$30,A10,$B$6:$B$30,"<="&B10) | K10: =SUMIFS($F$6:$F$30,$A$6:$A$30,A10,$B$6:$B$30,"<="&B10)
A11: Joalheria Brilho Eterno | B11: 3 | C11: Escritório | D11: Fechadura | E11: 960 | F11: 800 | G11: 3 | H11: =MAX(0.5,E11/MAX(1,$C$2)) | I11: =G11*(1-Config!$B$7*MIN(1,$C$3/100))*H11 | J11: =SUMIFS($I$6:$I$30,$A$6:$A$30,A11,$B$6:$B$30,"<="&B11) | K11: =SUMIFS($F$6:$F$30,$A$6:$A$30,A11,$B$6:$B$30,"<="&B11)
A12: Joalheria Brilho Eterno | B12: 4 | C12: Cofre | D12: Sistema | E12: 1120 | F12: 1500 | G12: 4 | H12: =MAX(0.5,E12/MAX(1,$C$2)) | I12: =G12*(1-Config!$B$7*MIN(1,$C$3/100))*H12 | J12: =SUMIFS($I$6:$I$30,$A$6:$A$30,A12,$B$6:$B$30,"<="&B12) | K12: =SUMIFS($F$6:$F$30,$A$6:$A$30,A12,$B$6:$B$30,"<="&B12)
A13: Casa de Câmbio Dólar Fácil | B13: 1 | C13: Fachada | D13: Fechadura | E13: 1120 | F13: 1500 | G13: 3 | H13: =MAX(0.5,E13/MAX(1,$C$2)) | I13: =G13*(1-Config!$B$7*MIN(1,$C$3/100))*H13 | J13: =SUMIFS($I$6:$I$30,$A$6:$A$30,A13,$B$6:$B$30,"<="&B13) | K13: =SUMIFS($F$6:$F$30,$A$6:$A$30,A13,$B$6:$B$30,"<="&B13)
A14: Casa de Câmbio Dólar Fácil | B14: 2 | C14: Balcão | D14: Pessoa | E14: 1260 | F14: 2500 | G14: 3.5 | H14: =MAX(0.5,E14/MAX(1,$C$2)) | I14: =G14*(1-Config!$B$7*MIN(1,$C$3/100))*H14 | J14: =SUMIFS($I$6:$I$30,$A$6:$A$30,A14,$B$6:$B$30,"<="&B14) | K14: =SUMIFS($F$6:$F$30,$A$6:$A$30,A14,$B$6:$B$30,"<="&B14)
A15: Casa de Câmbio Dólar Fácil | B15: 3 | C15: Corredor | D15: Sistema | E15: 1330 | F15: 3000 | G15: 4 | H15: =MAX(0.5,E15/MAX(1,$C$2)) | I15: =G15*(1-Config!$B$7*MIN(1,$C$3/100))*H15 | J15: =SUMIFS($I$6:$I$30,$A$6:$A$30,A15,$B$6:$B$30,"<="&B15) | K15: =SUMIFS($F$6:$F$30,$A$6:$A$30,A15,$B$6:$B$30,"<="&B15)
A16: Casa de Câmbio Dólar Fácil | B16: 4 | C16: Escritório do Gerente | D16: Pessoa | E16: 1470 | F16: 4000 | G16: 4 | H16: =MAX(0.5,E16/MAX(1,$C$2)) | I16: =G16*(1-Config!$B$7*MIN(1,$C$3/100))*H16 | J16: =SUMIFS($I$6:$I$30,$A$6:$A$30,A16,$B$6:$B$30,"<="&B16) | K16: =SUMIFS($F$6:$F$30,$A$6:$A$30,A16,$B$6:$B$30,"<="&B16)
A17: Casa de Câmbio Dólar Fácil | B17: 5 | C17: Cofre | D17: Fechadura | E17: 1680 | F17: 7000 | G17: 5 | H17: =MAX(0.5,E17/MAX(1,$C$2)) | I17: =G17*(1-Config!$B$7*MIN(1,$C$3/100))*H17 | J17: =SUMIFS($I$6:$I$30,$A$6:$A$30,A17,$B$6:$B$30,"<="&B17) | K17: =SUMIFS($F$6:$F$30,$A$6:$A$30,A17,$B$6:$B$30,"<="&B17)
... A30: Banco Central de Nova Guanabara | B30: 7 | C30: Cofre Central | D30: Fechadura | E30: 2280 | F30: 250000 | G30: 5.6 | H30: =MAX(0.5,E30/MAX(1,$C$2)) | I30: =G30*(1-Config!$B$7*MIN(1,$C$3/100))*H30 | J30: =SUMIFS($I$6:$I$30,$A$6:$A$30,A30,$B$6:$B$30,"<="&B30) | K30: =SUMIFS($F$6:$F$30,$A$6:$A$30,A30,$B$6:$B$30,"<="&B30)
A33: Resumo por golpe (cenário da aba Config)
A34: Golpe | B34: Salas | C34: Loot total | D34: Tempo total | E34: Alerta total | F34: Sirene? | G34: Pagamento (Lavanderia) | H34: Cr$ por minuto
A35: Lotérica do Seu Zé | B35: =COUNTIF($A$6:$A$30,A35) | C35: =SUMIF($A$6:$A$30,A35,$F$6:$F$30) | D35: =SUMIF($A$6:$A$30,A35,$H$6:$H$30) | E35: =SUMIF($A$6:$A$30,A35,$I$6:$I$30) | F35: =IF(E35>=100,"toca","não toca") | G35: =C35*(1+Config!$B$29*Upgrades!$G$10/100) | H35: =IF(D35>0,G35/(D35/60),0)
A36: Joalheria Brilho Eterno | B36: =COUNTIF($A$6:$A$30,A36) | C36: =SUMIF($A$6:$A$30,A36,$F$6:$F$30) | D36: =SUMIF($A$6:$A$30,A36,$H$6:$H$30) | E36: =SUMIF($A$6:$A$30,A36,$I$6:$I$30) | F36: =IF(E36>=100,"toca","não toca") | G36: =C36*(1+Config!$B$29*Upgrades!$G$10/100) | H36: =IF(D36>0,G36/(D36/60),0)
A37: Casa de Câmbio Dólar Fácil | B37: =COUNTIF($A$6:$A$30,A37) | C37: =SUMIF($A$6:$A$30,A37,$F$6:$F$30) | D37: =SUMIF($A$6:$A$30,A37,$H$6:$H$30) | E37: =SUMIF($A$6:$A$30,A37,$I$6:$I$30) | F37: =IF(E37>=100,"toca","não toca") | G37: =C37*(1+Config!$B$29*Upgrades!$G$10/100) | H37: =IF(D37>0,G37/(D37/60),0)
A38: Cassino Clandestino | B38: =COUNTIF($A$6:$A$30,A38) | C38: =SUMIF($A$6:$A$30,A38,$F$6:$F$30) | D38: =SUMIF($A$6:$A$30,A38,$H$6:$H$30) | E38: =SUMIF($A$6:$A$30,A38,$I$6:$I$30) | F38: =IF(E38>=100,"toca","não toca") | G38: =C38*(1+Config!$B$29*Upgrades!$G$10/100) | H38: =IF(D38>0,G38/(D38/60),0)
A39: Banco Central de Nova Guanabara | B39: =COUNTIF($A$6:$A$30,A39) | C39: =SUMIF($A$6:$A$30,A39,$F$6:$F$30) | D39: =SUMIF($A$6:$A$30,A39,$H$6:$H$30) | E39: =SUMIF($A$6:$A$30,A39,$I$6:$I$30) | F39: =IF(E39>=100,"toca","não toca") | G39: =C39*(1+Config!$B$29*Upgrades!$G$10/100) | H39: =IF(D39>0,G39/(D39/60),0)
A41: Alerta total do golpe por nível da crew (com os upgrades do cenário). Vermelho = sirene sem habilidade.
A42: Golpe | B42: Nv 1 | C42: Nv 2 | D42: Nv 3 | E42: Nv 4 | F42: Nv 5 | G42: Nv 6 | H42: Nv 7 | I42: Nv 8 | J42: Nv 9 | K42: Nv 10
A43: Lotérica do Seu Zé | B43: =SUMPRODUCT(($A$6:$A$30=$A43)*$E$6:$E$30*$G$6:$G$30)*(1-Config!$B$7*MIN(1,(AVERAGE(Ladrões!$B$19:$B$21)*(1+Config!$B$28*Upgrades!$G$7/100))/100))/(AVERAGE(Ladrões!$B$12:$B$14)*(1+Config!$B$27*Upgrades!$G$6/100)) | C43: =SUMPRODUCT(($A$6:$A$30=$A43)*$E$6:$E$30*$G$6:$G$30)*(1-Config!$B$7*MIN(1,(AVERAGE(Ladrões!$C$19:$C$21)*(1+Config!$B$28*Upgrades!$G$7/100))/100))/(AVERAGE(Ladrões!$C$12:$C$14)*(1+Config!$B$27*Upgrades!$G$6/100)) | D43: =SUMPRODUCT(($A$6:$A$30=$A43)*$E$6:$E$30*$G$6:$G$30)*(1-Config!$B$7*MIN(1,(AVERAGE(Ladrões!$D$19:$D$21)*(1+Config!$B$28*Upgrades!$G$7/100))/100))/(AVERAGE(Ladrões!$D$12:$D$14)*(1+Config!$B$27*Upgrades!$G$6/100)) | E43: =SUMPRODUCT(($A$6:$A$30=$A43)*$E$6:$E$30*$G$6:$G$30)*(1-Config!$B$7*MIN(1,(AVERAGE(Ladrões!$E$19:$E$21)*(1+Config!$B$28*Upgrades!$G$7/100))/100))/(AVERAGE(Ladrões!$E$12:$E$14)*(1+Config!$B$27*Upgrades!$G$6/100)) | F43: =SUMPRODUCT(($A$6:$A$30=$A43)*$E$6:$E$30*$G$6:$G$30)*(1-Config!$B$7*MIN(1,(AVERAGE(Ladrões!$F$19:$F$21)*(1+Config!$B$28*Upgrades!$G$7/100))/100))/(AVERAGE(Ladrões!$F$12:$F$14)*(1+Config!$B$27*Upgrades!$G$6/100)) | G43: =SUMPRODUCT(($A$6:$A$30=$A43)*$E$6:$E$30*$G$6:$G$30)*(1-Config!$B$7*MIN(1,(AVERAGE(Ladrões!$G$19:$G$21)*(1+Config!$B$28*Upgrades!$G$7/100))/100))/(AVERAGE(Ladrões!$G$12:$G$14)*(1+Config!$B$27*Upgrades!$G$6/100)) | H43: =SUMPRODUCT(($A$6:$A$30=$A43)*$E$6:$E$30*$G$6:$G$30)*(1-Config!$B$7*MIN(1,(AVERAGE(Ladrões!$H$19:$H$21)*(1+Config!$B$28*Upgrades!$G$7/100))/100))/(AVERAGE(Ladrões!$H$12:$H$14)*(1+Config!$B$27*Upgrades!$G$6/100)) | I43: =SUMPRODUCT(($A$6:$A$30=$A43)*$E$6:$E$30*$G$6:$G$30)*(1-Config!$B$7*MIN(1,(AVERAGE(Ladrões!$I$19:$I$21)*(1+Config!$B$28*Upgrades!$G$7/100))/100))/(AVERAGE(Ladrões!$I$12:$I$14)*(1+Config!$B$27*Upgrades!$G$6/100)) | J43: =SUMPRODUCT(($A$6:$A$30=$A43)*$E$6:$E$30*$G$6:$G$30)*(1-Config!$B$7*MIN(1,(AVERAGE(Ladrões!$J$19:$J$21)*(1+Config!$B$28*Upgrades!$G$7/100))/100))/(AVERAGE(Ladrões!$J$12:$J$14)*(1+Config!$B$27*Upgrades!$G$6/100)) | K43: =SUMPRODUCT(($A$6:$A$30=$A43)*$E$6:$E$30*$G$6:$G$30)*(1-Config!$B$7*MIN(1,(AVERAGE(Ladrões!$K$19:$K$21)*(1+Config!$B$28*Upgrades!$G$7/100))/100))/(AVERAGE(Ladrões!$K$12:$K$14)*(1+Config!$B$27*Upgrades!$G$6/100))
A44: Joalheria Brilho Eterno | B44: =SUMPRODUCT(($A$6:$A$30=$A44)*$E$6:$E$30*$G$6:$G$30)*(1-Config!$B$7*MIN(1,(AVERAGE(Ladrões!$B$19:$B$21)*(1+Config!$B$28*Upgrades!$G$7/100))/100))/(AVERAGE(Ladrões!$B$12:$B$14)*(1+Config!$B$27*Upgrades!$G$6/100)) | C44: =SUMPRODUCT(($A$6:$A$30=$A44)*$E$6:$E$30*$G$6:$G$30)*(1-Config!$B$7*MIN(1,(AVERAGE(Ladrões!$C$19:$C$21)*(1+Config!$B$28*Upgrades!$G$7/100))/100))/(AVERAGE(Ladrões!$C$12:$C$14)*(1+Config!$B$27*Upgrades!$G$6/100)) | D44: =SUMPRODUCT(($A$6:$A$30=$A44)*$E$6:$E$30*$G$6:$G$30)*(1-Config!$B$7*MIN(1,(AVERAGE(Ladrões!$D$19:$D$21)*(1+Config!$B$28*Upgrades!$G$7/100))/100))/(AVERAGE(Ladrões!$D$12:$D$14)*(1+Config!$B$27*Upgrades!$G$6/100)) | E44: =SUMPRODUCT(($A$6:$A$30=$A44)*$E$6:$E$30*$G$6:$G$30)*(1-Config!$B$7*MIN(1,(AVERAGE(Ladrões!$E$19:$E$21)*(1+Config!$B$28*Upgrades!$G$7/100))/100))/(AVERAGE(Ladrões!$E$12:$E$14)*(1+Config!$B$27*Upgrades!$G$6/100)) | F44: =SUMPRODUCT(($A$6:$A$30=$A44)*$E$6:$E$30*$G$6:$G$30)*(1-Config!$B$7*MIN(1,(AVERAGE(Ladrões!$F$19:$F$21)*(1+Config!$B$28*Upgrades!$G$7/100))/100))/(AVERAGE(Ladrões!$F$12:$F$14)*(1+Config!$B$27*Upgrades!$G$6/100)) | G44: =SUMPRODUCT(($A$6:$A$30=$A44)*$E$6:$E$30*$G$6:$G$30)*(1-Config!$B$7*MIN(1,(AVERAGE(Ladrões!$G$19:$G$21)*(1+Config!$B$28*Upgrades!$G$7/100))/100))/(AVERAGE(Ladrões!$G$12:$G$14)*(1+Config!$B$27*Upgrades!$G$6/100)) | H44: =SUMPRODUCT(($A$6:$A$30=$A44)*$E$6:$E$30*$G$6:$G$30)*(1-Config!$B$7*MIN(1,(AVERAGE(Ladrões!$H$19:$H$21)*(1+Config!$B$28*Upgrades!$G$7/100))/100))/(AVERAGE(Ladrões!$H$12:$H$14)*(1+Config!$B$27*Upgrades!$G$6/100)) | I44: =SUMPRODUCT(($A$6:$A$30=$A44)*$E$6:$E$30*$G$6:$G$30)*(1-Config!$B$7*MIN(1,(AVERAGE(Ladrões!$I$19:$I$21)*(1+Config!$B$28*Upgrades!$G$7/100))/100))/(AVERAGE(Ladrões!$I$12:$I$14)*(1+Config!$B$27*Upgrades!$G$6/100)) | J44: =SUMPRODUCT(($A$6:$A$30=$A44)*$E$6:$E$30*$G$6:$G$30)*(1-Config!$B$7*MIN(1,(AVERAGE(Ladrões!$J$19:$J$21)*(1+Config!$B$28*Upgrades!$G$7/100))/100))/(AVERAGE(Ladrões!$J$12:$J$14)*(1+Config!$B$27*Upgrades!$G$6/100)) | K44: =SUMPRODUCT(($A$6:$A$30=$A44)*$E$6:$E$30*$G$6:$G$30)*(1-Config!$B$7*MIN(1,(AVERAGE(Ladrões!$K$19:$K$21)*(1+Config!$B$28*Upgrades!$G$7/100))/100))/(AVERAGE(Ladrões!$K$12:$K$14)*(1+Config!$B$27*Upgrades!$G$6/100))
A45: Casa de Câmbio Dólar Fácil | B45: =SUMPRODUCT(($A$6:$A$30=$A45)*$E$6:$E$30*$G$6:$G$30)*(1-Config!$B$7*MIN(1,(AVERAGE(Ladrões!$B$19:$B$21)*(1+Config!$B$28*Upgrades!$G$7/100))/100))/(AVERAGE(Ladrões!$B$12:$B$14)*(1+Config!$B$27*Upgrades!$G$6/100)) | C45: =SUMPRODUCT(($A$6:$A$30=$A45)*$E$6:$E$30*$G$6:$G$30)*(1-Config!$B$7*MIN(1,(AVERAGE(Ladrões!$C$19:$C$21)*(1+Config!$B$28*Upgrades!$G$7/100))/100))/(AVERAGE(Ladrões!$C$12:$C$14)*(1+Config!$B$27*Upgrades!$G$6/100)) | D45: =SUMPRODUCT(($A$6:$A$30=$A45)*$E$6:$E$30*$G$6:$G$30)*(1-Config!$B$7*MIN(1,(AVERAGE(Ladrões!$D$19:$D$21)*(1+Config!$B$28*Upgrades!$G$7/100))/100))/(AVERAGE(Ladrões!$D$12:$D$14)*(1+Config!$B$27*Upgrades!$G$6/100)) | E45: =SUMPRODUCT(($A$6:$A$30=$A45)*$E$6:$E$30*$G$6:$G$30)*(1-Config!$B$7*MIN(1,(AVERAGE(Ladrões!$E$19:$E$21)*(1+Config!$B$28*Upgrades!$G$7/100))/100))/(AVERAGE(Ladrões!$E$12:$E$14)*(1+Config!$B$27*Upgrades!$G$6/100)) | F45: =SUMPRODUCT(($A$6:$A$30=$A45)*$E$6:$E$30*$G$6:$G$30)*(1-Config!$B$7*MIN(1,(AVERAGE(Ladrões!$F$19:$F$21)*(1+Config!$B$28*Upgrades!$G$7/100))/100))/(AVERAGE(Ladrões!$F$12:$F$14)*(1+Config!$B$27*Upgrades!$G$6/100)) | G45: =SUMPRODUCT(($A$6:$A$30=$A45)*$E$6:$E$30*$G$6:$G$30)*(1-Config!$B$7*MIN(1,(AVERAGE(Ladrões!$G$19:$G$21)*(1+Config!$B$28*Upgrades!$G$7/100))/100))/(AVERAGE(Ladrões!$G$12:$G$14)*(1+Config!$B$27*Upgrades!$G$6/100)) | H45: =SUMPRODUCT(($A$6:$A$30=$A45)*$E$6:$E$30*$G$6:$G$30)*(1-Config!$B$7*MIN(1,(AVERAGE(Ladrões!$H$19:$H$21)*(1+Config!$B$28*Upgrades!$G$7/100))/100))/(AVERAGE(Ladrões!$H$12:$H$14)*(1+Config!$B$27*Upgrades!$G$6/100)) | I45: =SUMPRODUCT(($A$6:$A$30=$A45)*$E$6:$E$30*$G$6:$G$30)*(1-Config!$B$7*MIN(1,(AVERAGE(Ladrões!$I$19:$I$21)*(1+Config!$B$28*Upgrades!$G$7/100))/100))/(AVERAGE(Ladrões!$I$12:$I$14)*(1+Config!$B$27*Upgrades!$G$6/100)) | J45: =SUMPRODUCT(($A$6:$A$30=$A45)*$E$6:$E$30*$G$6:$G$30)*(1-Config!$B$7*MIN(1,(AVERAGE(Ladrões!$J$19:$J$21)*(1+Config!$B$28*Upgrades!$G$7/100))/100))/(AVERAGE(Ladrões!$J$12:$J$14)*(1+Config!$B$27*Upgrades!$G$6/100)) | K45: =SUMPRODUCT(($A$6:$A$30=$A45)*$E$6:$E$30*$G$6:$G$30)*(1-Config!$B$7*MIN(1,(AVERAGE(Ladrões!$K$19:$K$21)*(1+Config!$B$28*Upgrades!$G$7/100))/100))/(AVERAGE(Ladrões!$K$12:$K$14)*(1+Config!$B$27*Upgrades!$G$6/100))
A46: Cassino Clandestino | B46: =SUMPRODUCT(($A$6:$A$30=$A46)*$E$6:$E$30*$G$6:$G$30)*(1-Config!$B$7*MIN(1,(AVERAGE(Ladrões!$B$19:$B$21)*(1+Config!$B$28*Upgrades!$G$7/100))/100))/(AVERAGE(Ladrões!$B$12:$B$14)*(1+Config!$B$27*Upgrades!$G$6/100)) | C46: =SUMPRODUCT(($A$6:$A$30=$A46)*$E$6:$E$30*$G$6:$G$30)*(1-Config!$B$7*MIN(1,(AVERAGE(Ladrões!$C$19:$C$21)*(1+Config!$B$28*Upgrades!$G$7/100))/100))/(AVERAGE(Ladrões!$C$12:$C$14)*(1+Config!$B$27*Upgrades!$G$6/100)) | D46: =SUMPRODUCT(($A$6:$A$30=$A46)*$E$6:$E$30*$G$6:$G$30)*(1-Config!$B$7*MIN(1,(AVERAGE(Ladrões!$D$19:$D$21)*(1+Config!$B$28*Upgrades!$G$7/100))/100))/(AVERAGE(Ladrões!$D$12:$D$14)*(1+Config!$B$27*Upgrades!$G$6/100)) | E46: =SUMPRODUCT(($A$6:$A$30=$A46)*$E$6:$E$30*$G$6:$G$30)*(1-Config!$B$7*MIN(1,(AVERAGE(Ladrões!$E$19:$E$21)*(1+Config!$B$28*Upgrades!$G$7/100))/100))/(AVERAGE(Ladrões!$E$12:$E$14)*(1+Config!$B$27*Upgrades!$G$6/100)) | F46: =SUMPRODUCT(($A$6:$A$30=$A46)*$E$6:$E$30*$G$6:$G$30)*(1-Config!$B$7*MIN(1,(AVERAGE(Ladrões!$F$19:$F$21)*(1+Config!$B$28*Upgrades!$G$7/100))/100))/(AVERAGE(Ladrões!$F$12:$F$14)*(1+Config!$B$27*Upgrades!$G$6/100)) | G46: =SUMPRODUCT(($A$6:$A$30=$A46)*$E$6:$E$30*$G$6:$G$30)*(1-Config!$B$7*MIN(1,(AVERAGE(Ladrões!$G$19:$G$21)*(1+Config!$B$28*Upgrades!$G$7/100))/100))/(AVERAGE(Ladrões!$G$12:$G$14)*(1+Config!$B$27*Upgrades!$G$6/100)) | H46: =SUMPRODUCT(($A$6:$A$30=$A46)*$E$6:$E$30*$G$6:$G$30)*(1-Config!$B$7*MIN(1,(AVERAGE(Ladrões!$H$19:$H$21)*(1+Config!$B$28*Upgrades!$G$7/100))/100))/(AVERAGE(Ladrões!$H$12:$H$14)*(1+Config!$B$27*Upgrades!$G$6/100)) | I46: =SUMPRODUCT(($A$6:$A$30=$A46)*$E$6:$E$30*$G$6:$G$30)*(1-Config!$B$7*MIN(1,(AVERAGE(Ladrões!$I$19:$I$21)*(1+Config!$B$28*Upgrades!$G$7/100))/100))/(AVERAGE(Ladrões!$I$12:$I$14)*(1+Config!$B$27*Upgrades!$G$6/100)) | J46: =SUMPRODUCT(($A$6:$A$30=$A46)*$E$6:$E$30*$G$6:$G$30)*(1-Config!$B$7*MIN(1,(AVERAGE(Ladrões!$J$19:$J$21)*(1+Config!$B$28*Upgrades!$G$7/100))/100))/(AVERAGE(Ladrões!$J$12:$J$14)*(1+Config!$B$27*Upgrades!$G$6/100)) | K46: =SUMPRODUCT(($A$6:$A$30=$A46)*$E$6:$E$30*$G$6:$G$30)*(1-Config!$B$7*MIN(1,(AVERAGE(Ladrões!$K$19:$K$21)*(1+Config!$B$28*Upgrades!$G$7/100))/100))/(AVERAGE(Ladrões!$K$12:$K$14)*(1+Config!$B$27*Upgrades!$G$6/100))
A47: Banco Central de Nova Guanabara | B47: =SUMPRODUCT(($A$6:$A$30=$A47)*$E$6:$E$30*$G$6:$G$30)*(1-Config!$B$7*MIN(1,(AVERAGE(Ladrões!$B$19:$B$21)*(1+Config!$B$28*Upgrades!$G$7/100))/100))/(AVERAGE(Ladrões!$B$12:$B$14)*(1+Config!$B$27*Upgrades!$G$6/100)) | C47: =SUMPRODUCT(($A$6:$A$30=$A47)*$E$6:$E$30*$G$6:$G$30)*(1-Config!$B$7*MIN(1,(AVERAGE(Ladrões!$C$19:$C$21)*(1+Config!$B$28*Upgrades!$G$7/100))/100))/(AVERAGE(Ladrões!$C$12:$C$14)*(1+Config!$B$27*Upgrades!$G$6/100)) | D47: =SUMPRODUCT(($A$6:$A$30=$A47)*$E$6:$E$30*$G$6:$G$30)*(1-Config!$B$7*MIN(1,(AVERAGE(Ladrões!$D$19:$D$21)*(1+Config!$B$28*Upgrades!$G$7/100))/100))/(AVERAGE(Ladrões!$D$12:$D$14)*(1+Config!$B$27*Upgrades!$G$6/100)) | E47: =SUMPRODUCT(($A$6:$A$30=$A47)*$E$6:$E$30*$G$6:$G$30)*(1-Config!$B$7*MIN(1,(AVERAGE(Ladrões!$E$19:$E$21)*(1+Config!$B$28*Upgrades!$G$7/100))/100))/(AVERAGE(Ladrões!$E$12:$E$14)*(1+Config!$B$27*Upgrades!$G$6/100)) | F47: =SUMPRODUCT(($A$6:$A$30=$A47)*$E$6:$E$30*$G$6:$G$30)*(1-Config!$B$7*MIN(1,(AVERAGE(Ladrões!$F$19:$F$21)*(1+Config!$B$28*Upgrades!$G$7/100))/100))/(AVERAGE(Ladrões!$F$12:$F$14)*(1+Config!$B$27*Upgrades!$G$6/100)) | G47: =SUMPRODUCT(($A$6:$A$30=$A47)*$E$6:$E$30*$G$6:$G$30)*(1-Config!$B$7*MIN(1,(AVERAGE(Ladrões!$G$19:$G$21)*(1+Config!$B$28*Upgrades!$G$7/100))/100))/(AVERAGE(Ladrões!$G$12:$G$14)*(1+Config!$B$27*Upgrades!$G$6/100)) | H47: =SUMPRODUCT(($A$6:$A$30=$A47)*$E$6:$E$30*$G$6:$G$30)*(1-Config!$B$7*MIN(1,(AVERAGE(Ladrões!$H$19:$H$21)*(1+Config!$B$28*Upgrades!$G$7/100))/100))/(AVERAGE(Ladrões!$H$12:$H$14)*(1+Config!$B$27*Upgrades!$G$6/100)) | I47: =SUMPRODUCT(($A$6:$A$30=$A47)*$E$6:$E$30*$G$6:$G$30)*(1-Config!$B$7*MIN(1,(AVERAGE(Ladrões!$I$19:$I$21)*(1+Config!$B$28*Upgrades!$G$7/100))/100))/(AVERAGE(Ladrões!$I$12:$I$14)*(1+Config!$B$27*Upgrades!$G$6/100)) | J47: =SUMPRODUCT(($A$6:$A$30=$A47)*$E$6:$E$30*$G$6:$G$30)*(1-Config!$B$7*MIN(1,(AVERAGE(Ladrões!$J$19:$J$21)*(1+Config!$B$28*Upgrades!$G$7/100))/100))/(AVERAGE(Ladrões!$J$12:$J$14)*(1+Config!$B$27*Upgrades!$G$6/100)) | K47: =SUMPRODUCT(($A$6:$A$30=$A47)*$E$6:$E$30*$G$6:$G$30)*(1-Config!$B$7*MIN(1,(AVERAGE(Ladrões!$K$19:$K$21)*(1+Config!$B$28*Upgrades!$G$7/100))/100))/(AVERAGE(Ladrões!$K$12:$K$14)*(1+Config!$B$27*Upgrades!$G$6/100))
A48: Tempo total do golpe (s) por nível da crew
A49: Golpe | B49: Nv 1 | C49: Nv 2 | D49: Nv 3 | E49: Nv 4 | F49: Nv 5 | G49: Nv 6 | H49: Nv 7 | I49: Nv 8 | J49: Nv 9 | K49: Nv 10
A50: Lotérica do Seu Zé | B50: =SUMPRODUCT(($A$6:$A$30=$A50)*$E$6:$E$30)/(AVERAGE(Ladrões!$B$12:$B$14)*(1+Config!$B$27*Upgrades!$G$6/100)) | C50: =SUMPRODUCT(($A$6:$A$30=$A50)*$E$6:$E$30)/(AVERAGE(Ladrões!$C$12:$C$14)*(1+Config!$B$27*Upgrades!$G$6/100)) | D50: =SUMPRODUCT(($A$6:$A$30=$A50)*$E$6:$E$30)/(AVERAGE(Ladrões!$D$12:$D$14)*(1+Config!$B$27*Upgrades!$G$6/100)) | E50: =SUMPRODUCT(($A$6:$A$30=$A50)*$E$6:$E$30)/(AVERAGE(Ladrões!$E$12:$E$14)*(1+Config!$B$27*Upgrades!$G$6/100)) | F50: =SUMPRODUCT(($A$6:$A$30=$A50)*$E$6:$E$30)/(AVERAGE(Ladrões!$F$12:$F$14)*(1+Config!$B$27*Upgrades!$G$6/100)) | G50: =SUMPRODUCT(($A$6:$A$30=$A50)*$E$6:$E$30)/(AVERAGE(Ladrões!$G$12:$G$14)*(1+Config!$B$27*Upgrades!$G$6/100)) | H50: =SUMPRODUCT(($A$6:$A$30=$A50)*$E$6:$E$30)/(AVERAGE(Ladrões!$H$12:$H$14)*(1+Config!$B$27*Upgrades!$G$6/100)) | I50: =SUMPRODUCT(($A$6:$A$30=$A50)*$E$6:$E$30)/(AVERAGE(Ladrões!$I$12:$I$14)*(1+Config!$B$27*Upgrades!$G$6/100)) | J50: =SUMPRODUCT(($A$6:$A$30=$A50)*$E$6:$E$30)/(AVERAGE(Ladrões!$J$12:$J$14)*(1+Config!$B$27*Upgrades!$G$6/100)) | K50: =SUMPRODUCT(($A$6:$A$30=$A50)*$E$6:$E$30)/(AVERAGE(Ladrões!$K$12:$K$14)*(1+Config!$B$27*Upgrades!$G$6/100))
A51: Joalheria Brilho Eterno | B51: =SUMPRODUCT(($A$6:$A$30=$A51)*$E$6:$E$30)/(AVERAGE(Ladrões!$B$12:$B$14)*(1+Config!$B$27*Upgrades!$G$6/100)) | C51: =SUMPRODUCT(($A$6:$A$30=$A51)*$E$6:$E$30)/(AVERAGE(Ladrões!$C$12:$C$14)*(1+Config!$B$27*Upgrades!$G$6/100)) | D51: =SUMPRODUCT(($A$6:$A$30=$A51)*$E$6:$E$30)/(AVERAGE(Ladrões!$D$12:$D$14)*(1+Config!$B$27*Upgrades!$G$6/100)) | E51: =SUMPRODUCT(($A$6:$A$30=$A51)*$E$6:$E$30)/(AVERAGE(Ladrões!$E$12:$E$14)*(1+Config!$B$27*Upgrades!$G$6/100)) | F51: =SUMPRODUCT(($A$6:$A$30=$A51)*$E$6:$E$30)/(AVERAGE(Ladrões!$F$12:$F$14)*(1+Config!$B$27*Upgrades!$G$6/100)) | G51: =SUMPRODUCT(($A$6:$A$30=$A51)*$E$6:$E$30)/(AVERAGE(Ladrões!$G$12:$G$14)*(1+Config!$B$27*Upgrades!$G$6/100)) | H51: =SUMPRODUCT(($A$6:$A$30=$A51)*$E$6:$E$30)/(AVERAGE(Ladrões!$H$12:$H$14)*(1+Config!$B$27*Upgrades!$G$6/100)) | I51: =SUMPRODUCT(($A$6:$A$30=$A51)*$E$6:$E$30)/(AVERAGE(Ladrões!$I$12:$I$14)*(1+Config!$B$27*Upgrades!$G$6/100)) | J51: =SUMPRODUCT(($A$6:$A$30=$A51)*$E$6:$E$30)/(AVERAGE(Ladrões!$J$12:$J$14)*(1+Config!$B$27*Upgrades!$G$6/100)) | K51: =SUMPRODUCT(($A$6:$A$30=$A51)*$E$6:$E$30)/(AVERAGE(Ladrões!$K$12:$K$14)*(1+Config!$B$27*Upgrades!$G$6/100))
A52: Casa de Câmbio Dólar Fácil | B52: =SUMPRODUCT(($A$6:$A$30=$A52)*$E$6:$E$30)/(AVERAGE(Ladrões!$B$12:$B$14)*(1+Config!$B$27*Upgrades!$G$6/100)) | C52: =SUMPRODUCT(($A$6:$A$30=$A52)*$E$6:$E$30)/(AVERAGE(Ladrões!$C$12:$C$14)*(1+Config!$B$27*Upgrades!$G$6/100)) | D52: =SUMPRODUCT(($A$6:$A$30=$A52)*$E$6:$E$30)/(AVERAGE(Ladrões!$D$12:$D$14)*(1+Config!$B$27*Upgrades!$G$6/100)) | E52: =SUMPRODUCT(($A$6:$A$30=$A52)*$E$6:$E$30)/(AVERAGE(Ladrões!$E$12:$E$14)*(1+Config!$B$27*Upgrades!$G$6/100)) | F52: =SUMPRODUCT(($A$6:$A$30=$A52)*$E$6:$E$30)/(AVERAGE(Ladrões!$F$12:$F$14)*(1+Config!$B$27*Upgrades!$G$6/100)) | G52: =SUMPRODUCT(($A$6:$A$30=$A52)*$E$6:$E$30)/(AVERAGE(Ladrões!$G$12:$G$14)*(1+Config!$B$27*Upgrades!$G$6/100)) | H52: =SUMPRODUCT(($A$6:$A$30=$A52)*$E$6:$E$30)/(AVERAGE(Ladrões!$H$12:$H$14)*(1+Config!$B$27*Upgrades!$G$6/100)) | I52: =SUMPRODUCT(($A$6:$A$30=$A52)*$E$6:$E$30)/(AVERAGE(Ladrões!$I$12:$I$14)*(1+Config!$B$27*Upgrades!$G$6/100)) | J52: =SUMPRODUCT(($A$6:$A$30=$A52)*$E$6:$E$30)/(AVERAGE(Ladrões!$J$12:$J$14)*(1+Config!$B$27*Upgrades!$G$6/100)) | K52: =SUMPRODUCT(($A$6:$A$30=$A52)*$E$6:$E$30)/(AVERAGE(Ladrões!$K$12:$K$14)*(1+Config!$B$27*Upgrades!$G$6/100))
A53: Cassino Clandestino | B53: =SUMPRODUCT(($A$6:$A$30=$A53)*$E$6:$E$30)/(AVERAGE(Ladrões!$B$12:$B$14)*(1+Config!$B$27*Upgrades!$G$6/100)) | C53: =SUMPRODUCT(($A$6:$A$30=$A53)*$E$6:$E$30)/(AVERAGE(Ladrões!$C$12:$C$14)*(1+Config!$B$27*Upgrades!$G$6/100)) | D53: =SUMPRODUCT(($A$6:$A$30=$A53)*$E$6:$E$30)/(AVERAGE(Ladrões!$D$12:$D$14)*(1+Config!$B$27*Upgrades!$G$6/100)) | E53: =SUMPRODUCT(($A$6:$A$30=$A53)*$E$6:$E$30)/(AVERAGE(Ladrões!$E$12:$E$14)*(1+Config!$B$27*Upgrades!$G$6/100)) | F53: =SUMPRODUCT(($A$6:$A$30=$A53)*$E$6:$E$30)/(AVERAGE(Ladrões!$F$12:$F$14)*(1+Config!$B$27*Upgrades!$G$6/100)) | G53: =SUMPRODUCT(($A$6:$A$30=$A53)*$E$6:$E$30)/(AVERAGE(Ladrões!$G$12:$G$14)*(1+Config!$B$27*Upgrades!$G$6/100)) | H53: =SUMPRODUCT(($A$6:$A$30=$A53)*$E$6:$E$30)/(AVERAGE(Ladrões!$H$12:$H$14)*(1+Config!$B$27*Upgrades!$G$6/100)) | I53: =SUMPRODUCT(($A$6:$A$30=$A53)*$E$6:$E$30)/(AVERAGE(Ladrões!$I$12:$I$14)*(1+Config!$B$27*Upgrades!$G$6/100)) | J53: =SUMPRODUCT(($A$6:$A$30=$A53)*$E$6:$E$30)/(AVERAGE(Ladrões!$J$12:$J$14)*(1+Config!$B$27*Upgrades!$G$6/100)) | K53: =SUMPRODUCT(($A$6:$A$30=$A53)*$E$6:$E$30)/(AVERAGE(Ladrões!$K$12:$K$14)*(1+Config!$B$27*Upgrades!$G$6/100))
A54: Banco Central de Nova Guanabara | B54: =SUMPRODUCT(($A$6:$A$30=$A54)*$E$6:$E$30)/(AVERAGE(Ladrões!$B$12:$B$14)*(1+Config!$B$27*Upgrades!$G$6/100)) | C54: =SUMPRODUCT(($A$6:$A$30=$A54)*$E$6:$E$30)/(AVERAGE(Ladrões!$C$12:$C$14)*(1+Config!$B$27*Upgrades!$G$6/100)) | D54: =SUMPRODUCT(($A$6:$A$30=$A54)*$E$6:$E$30)/(AVERAGE(Ladrões!$D$12:$D$14)*(1+Config!$B$27*Upgrades!$G$6/100)) | E54: =SUMPRODUCT(($A$6:$A$30=$A54)*$E$6:$E$30)/(AVERAGE(Ladrões!$E$12:$E$14)*(1+Config!$B$27*Upgrades!$G$6/100)) | F54: =SUMPRODUCT(($A$6:$A$30=$A54)*$E$6:$E$30)/(AVERAGE(Ladrões!$F$12:$F$14)*(1+Config!$B$27*Upgrades!$G$6/100)) | G54: =SUMPRODUCT(($A$6:$A$30=$A54)*$E$6:$E$30)/(AVERAGE(Ladrões!$G$12:$G$14)*(1+Config!$B$27*Upgrades!$G$6/100)) | H54: =SUMPRODUCT(($A$6:$A$30=$A54)*$E$6:$E$30)/(AVERAGE(Ladrões!$H$12:$H$14)*(1+Config!$B$27*Upgrades!$G$6/100)) | I54: =SUMPRODUCT(($A$6:$A$30=$A54)*$E$6:$E$30)/(AVERAGE(Ladrões!$I$12:$I$14)*(1+Config!$B$27*Upgrades!$G$6/100)) | J54: =SUMPRODUCT(($A$6:$A$30=$A54)*$E$6:$E$30)/(AVERAGE(Ladrões!$J$12:$J$14)*(1+Config!$B$27*Upgrades!$G$6/100)) | K54: =SUMPRODUCT(($A$6:$A$30=$A54)*$E$6:$E$30)/(AVERAGE(Ladrões!$K$12:$K$14)*(1+Config!$B$27*Upgrades!$G$6/100))
A55: As habilidades ajudam a passar dos 100: Lábia −25, Loop na câmera 15 s sem alerta, Pé-de-cabra limpa uma sala de Fechadura (+15).

Sheet Bicos
A1: Renda dos bicos e ganho offline
A3: Renda base do bico (Cr$/s) | B3: 3
A4: Multiplicador do tipo certo | B4: 2
A5: Bônus por nível do ladrão | B5: 0.1
A6: Ponto de bico (+%) | B6: =Config!$B$30*Upgrades!$G$12
A8: Nível do ladrão | B8: Tipo errado (Cr$/s) | C8: Tipo certo (Cr$/s) | D8: Tipo certo (Cr$/min)
A9: 1 | B9: =$B$3*(1+$B$5*(A9-1))*(1+$B$6/100) | C9: =B9*$B$4 | D9: =C9*60
A10: 2 | B10: =$B$3*(1+$B$5*(A10-1))*(1+$B$6/100) | C10: =B10*$B$4 | D10: =C10*60
A11: 3 | B11: =$B$3*(1+$B$5*(A11-1))*(1+$B$6/100) | C11: =B11*$B$4 | D11: =C11*60
A12: 4 | B12: =$B$3*(1+$B$5*(A12-1))*(1+$B$6/100) | C12: =B12*$B$4 | D12: =C12*60
A13: 5 | B13: =$B$3*(1+$B$5*(A13-1))*(1+$B$6/100) | C13: =B13*$B$4 | D13: =C13*60
A14: 6 | B14: =$B$3*(1+$B$5*(A14-1))*(1+$B$6/100) | C14: =B14*$B$4 | D14: =C14*60
A15: 7 | B15: =$B$3*(1+$B$5*(A15-1))*(1+$B$6/100) | C15: =B15*$B$4 | D15: =C15*60
A16: 8 | B16: =$B$3*(1+$B$5*(A16-1))*(1+$B$6/100) | C16: =B16*$B$4 | D16: =C16*60
A17: 9 | B17: =$B$3*(1+$B$5*(A17-1))*(1+$B$6/100) | C17: =B17*$B$4 | D17: =C17*60
A18: 10 | B18: =$B$3*(1+$B$5*(A18-1))*(1+$B$6/100) | C18: =B18*$B$4 | D18: =C18*60
A20: Catar latinha (Cr$/s) | B20: =Config!$B$17*(1+$B$6/100)
A22: Ganho offline
A23: Horas fora | B23: Renda/s ao sair | C23: Ganho
A24: 0.5 | B24: =B20+2*C11 | C24: =B24*MIN(A24,Config!$B$18)*3600*Config!$B$19
A25: 1 | B25: =B20+2*C11 | C25: =B25*MIN(A25,Config!$B$18)*3600*Config!$B$19
A26: 2 | B26: =B20+2*C11 | C26: =B26*MIN(A26,Config!$B$18)*3600*Config!$B$19
A27: 4 | B27: =B20+2*C11 | C27: =B27*MIN(A27,Config!$B$18)*3600*Config!$B$19
A28: 8 | B28: =B20+2*C11 | C28: =B28*MIN(A28,Config!$B$18)*3600*Config!$B$19

Sheet Recrutas
A1: Recruta: custo = base × crescimento^(nível − 1)
A3: Nível do recruta | B3: Custo
A4: 1 | B4: =ROUND(Config!$B$15*Config!$B$16^(A4-1),0)
A5: 2 | B5: =ROUND(Config!$B$15*Config!$B$16^(A5-1),0)
A6: 3 | B6: =ROUND(Config!$B$15*Config!$B$16^(A6-1),0)
A7: 4 | B7: =ROUND(Config!$B$15*Config!$B$16^(A7-1),0)
A8: 5 | B8: =ROUND(Config!$B$15*Config!$B$16^(A8-1),0)
A9: 6 | B9: =ROUND(Config!$B$15*Config!$B$16^(A9-1),0)
A11: Nível sorteado vai de 1 a 1 + Contatos (Fama Lenda soma de graça).

Sheet Curva
A1: Curva até o Banco Central: metas × simulação
A2: Fonte: docs/balanceamento/simulador.py em 25/10/2026 (jogador perfeito: é o piso; o playtest #43 dá o tempo real).
A4: Marco | B4: Meta (min) | C4: Antes (v0) | D4: v1 com habilidades | E4: v1 sem habilidades
A5: Lotérica concluída (Joalheria liberada) | B5: ~3 (com tutorial) | C5: 0.8 | D5: 0.8 | E5: 1
A6: Joalheria concluída (Câmbio liberado) | B6: ~10 | C6: 2.2 | D6: 3.8 | E6: 11.4
A7: Câmbio concluído (Cassino liberado) | B7: ~20 | C7: 5.6 | D7: 12.1 | E7: 36.5
A8: Cassino concluído | B8: — | C8: 55.6 | D8: 26.1 | E8: 74.4
A9: Banco Central concluído (1º prestígio) | B9: 40–60 | C9: não conclui em 120 | D9: 48.8 | E9: 88.4
A11: O que mudou do v0 pro v1 (HeistDef)
A12: Golpe | B12: Dificuldade | C12: Alerta/s | D12: Por quê
A13: Joalheria | B13: ×1,6 | C13: igual | D13: Câmbio liberava em 2 min; agora pede subir de nível antes
A14: Câmbio | B14: ×1,4 | C14: igual | D14: Mesmo motivo: o meio do jogo passava rápido demais
A15: Cassino | B15: ×0,9 | C15: ×0,8 | D15: Parede: nem com tudo no máximo fechava sem sirene
A16: Banco Central | B16: ×0,6 | C16: ×0,7 | D16: Salas de 22–36 s (regra é 5–20 s) e nunca era concluído
